{
  "name": "USA Builders Email List",
  "slug": "usa-builders-email-list",
  "url": "https://b2bdataindex.com/targeted-lists/usa-builders-email-list/",
  "audience_size": 3271453,
  "sub_type": "general",
  "geographic_distribution": {
    "United States": 50,
    "United Kingdom": 12,
    "Canada": 9,
    "Australia": 3,
    "Rest of World": 26
  },
  "audience_segments": {
    "Primary Audience": 14,
    "Secondary Segment": 5,
    "Active Subscribers": 31,
    "Interest-Verified": 10,
    "Premium Contacts": 30,
    "Recent Additions": 10
  },
  "benchmarks": {
    "open_rate": "25.3%",
    "reply_rate": "7.1%",
    "ctr": "9.2%"
  },
  "verification_rate": "92%",
  "last_verified": "Q1-2026",
  "product_url": "https://leadsblue.com/leads/usa-builders-construction-email-leads-database/"
}